{
  "administration": {
    "secteurs": {
      "titreSecteur": "Liste des secteurs",
      "table": {
        "tableTitle": "Administration des secteurs",
        "captionText": "Liste des secteurs avec fonctionnalités d'ajout/modification/suppression d'un secteur, de trier les secteurs",
        "emptyResult": "Aucun secteur présent",
        "addTitle": "Ajouter un secteur",
        "sortMultiTitle": "Tri multicolonne par date de création décroissant en premier et ensuite par auteur croissant."
      },
      "nom": "Nom",
      "description": "Description",
      "dateCr": "Date de création",
      "dateMaj": "Date de mise à jour",
      "auteur": "Auteur de la création",
      "quickUpdate": "Edition rapide",
      "quickUpdateTitle": "Modification rapide du secteur {nom}",
      "modification": "Modification",
      "modificationTitle": "Modification du secteur {nom}",
      "suppression": "Suppression",
      "suppressionAlt": "Suppression du secteur {desc}",
      "confirmationSuppression": "Etes-vous sûr(e) de vouloir supprimer ce secteur ?",
      "confirmationAnnulationAction": "Etes-vous sûr(e) de vouloir annuler l'action en cours ?",
      "editionRapide": "Edition rapide",
      "editer": "Editer",
      "enregistrer": "Enregistrer",
      "annuler": "Annuler",
      "suppressionTitle": "Suppression de secteur",
      "annulationTitle": "Annulation",
      "form": {
        "nomRequired": "Le champ « Nom » est obligatoire. Veuillez saisir ce champ.",
        "descRequired": "Le champ « Description » est obligatoire. Veuillez saisir ce champ.",
        "dateRequired": "Le champ « Date de mise à jour » est obligatoire. Veuillez saisir ce champ.",
        "fields": {
          "desc": {
            "label": "Description",
            "required": "Le champ « Description » est obligatoire. Veuillez saisir ce champ.",
            "maxLength": "Le champ « Description » est limité à 200 caractères. Veuillez corriger votre saisie."
          },
          "nom": {
            "label": "Nom",
            "required": "Le champ « Nom » est obligatoire. Veuillez saisir ce champ.",
            "maxLength": "Le champ « Nom » est limité à 50 caractères. Veuillez corriger votre saisie."
          }
        },
        "validTitle": "Validation de la saisie du secteur",
        "cancelTitle": "Annulation de la saisie du secteur"
      }
    },
    "modification": "Modification d'un secteur",
    "ajout": "Ajout d'un secteur",
    "closeModification": "Abandonner la modification d'un secteur",
    "closeAjout": "Abandonner l'ajout d'un secteur",
    "validTitle": "Ajout d'un secteur",
    "cancelTitle": "Annulation de l'ajout d'un secteur"
  },
  "repartitionPage": {
    "title": "Répartition des secteurs sous forme d'un graphique",
    "description": "Représentation graphique de la répartition des secteurs",
    "type": {
      "doughnut": "donut",
      "pie": "lune",
      "polarArea": "polaire"
    }
  }
}